{
  "id": 6114,
  "title": "Heroic: Warmaster Blackhorn",
  "points": 10,
  "description": "Defeat Warmaster Blackhorn in Dragon Soul on Heroic Difficulty.",
  "rewardItems": [],
  "icon": "achievment_boss_blackhorn",
  "criteria": [
    {
      "id": 18565,
      "description": "Warmaster Blackhorn (10H)",
      "orderIndex": 1,
      "max": 1
    },
    {
      "id": 18566,
      "description": "Warmaster Blackhorn (25H)",
      "orderIndex": 2,
      "max": 1
    }
  ],
  "accountWide": false,
  "factionId": 2
}
